desklog/__init__.py
desklog/__main__.py
desklog/check_dependencies.py
desklog/client.py
desklog/post_install.py
desklog/server.py
desklog-0.1.4.dist-info/licenses/LICENSE
desklog-0.1.4.dist-info/METADATA
desklog-0.1.4.dist-info/WHEEL
desklog-0.1.4.dist-info/entry_points.txt
desklog-0.1.4.dist-info/top_level.txt
desklog-0.1.4.dist-info/RECORD
